google_search_img.py
google_search_img-0.0.4.dist-info/METADATA
google_search_img-0.0.4.dist-info/WHEEL
google_search_img-0.0.4.dist-info/top_level.txt
google_search_img-0.0.4.dist-info/RECORD
