Metadata-Version: 2.1
Name: google-search-img
Version: 0.0.4
Summary: vidhi
Home-page: UNKNOWN
Author: haldiram mithaiwala
Author-email: dangerdhani@gmail.com
License: UNKNOWN
Keywords: python,hacking,cybersecurity,hacking tools,security testing,hacker
Platform: UNKNOWN
Classifier: Development Status :: 1 - Planning
Classifier: Intended Audience :: Developers
Classifier: Programming Language :: Python :: 3
Classifier: Operating System :: Unix
Classifier: Operating System :: MacOS :: MacOS X
Classifier: Operating System :: Microsoft :: Windows
